defs.vh
`define FLOORS 6

rtl/elevator_car.v
`include "rtl/defs.vh"

module elevator_car #(
    parameter ID = 0
) (
    input clk,
    input rst,
    input [`FLOORS-1:0] requests, // bitmask of floors requested for this car
    output reg [`FLOORS-1:0] pending, // internal pending mask
    output reg [2:0] current_floor, // enough bits for floors
    output reg moving // 1 if moving, 0 if idle
);

    // Simple model: on request set pending; move towards lowest-index set bit
    integer i;
    integer target;

    always @(posedge clk or posedge rst) begin
        if (rst) begin
            pending <= 0;
            current_floor <= 0;
            moving <= 0;
        end else begin
            // add new requests
            pending <= pending | requests;

            if (pending == 0) begin
                moving <= 0;
            end else begin
                moving <= 1;
                // find lowest-index set bit
                target = -1;
                for (i=0;i<`FLOORS;i=i+1) begin
                    if (pending[i]) begin
                        target = i;
                        i = `FLOORS; // exit loop
                    end
                end

                if (target != -1) begin
                    if (current_floor < target)
                        current_floor <= current_floor + 1;
                    else if (current_floor > target)
                        current_floor <= current_floor - 1;
                    else
                        pending[target] <= 0; // arrived, clear
                end
            end
        end
    end

endmodule

rtl/dual_elevator_controller.v
`include "rtl/defs.vh"

module dual_elevator_controller(
    input clk,
    input rst,
    input [`FLOORS-1:0] hall_up,   // hall calls up
    input [`FLOORS-1:0] hall_down, // hall calls down
    input [`FLOORS-1:0] car1_req,  // direct car requests
    input [`FLOORS-1:0] car2_req,
    output [`FLOORS-1:0] car1_assign, // requests assigned to car1
    output [`FLOORS-1:0] car2_assign,
    output [2:0] car1_floor,
    output [2:0] car2_floor,
    output car1_moving,
    output car2_moving
);

    // Simple scheduler: combine hall calls and car requests into a single request mask
    wire [`FLOORS-1:0] combined = hall_up | hall_down | car1_req | car2_req;

    // Very simple assignment: split floors 0..(FLOORS/2-1) -> car1, rest -> car2
    localparam MID = `FLOORS/2;

    reg [`FLOORS-1:0] assign1, assign2;

    integer j;
    always @(*) begin
        assign1 = 0; assign2 = 0;
        for (j=0;j<`FLOORS;j=j+1) begin
            if (j < MID)
                assign1[j] = combined[j];
            else
                assign2[j] = combined[j];
        end
    end

    // Instantiate elevator cars
    elevator_car #(.ID(1)) car1(
        .clk(clk), .rst(rst), .requests(assign1), .pending(), .current_floor(car1_floor), .moving(car1_moving)
    );

    elevator_car #(.ID(2)) car2(
        .clk(clk), .rst(rst), .requests(assign2), .pending(), .current_floor(car2_floor), .moving(car2_moving)
    );

    assign car1_assign = assign1;
    assign car2_assign = assign2;

endmodule

dual_elevator_tb.v
`timescale 1ns/1ps
`include "defs.vh"

module dual_elevator_tb;
    reg clk = 0;
    reg rst = 1;

    reg [`FLOORS-1:0] hall_up;
    reg [`FLOORS-1:0] hall_down;
    reg [`FLOORS-1:0] car1_req;
    reg [`FLOORS-1:0] car2_req;

    wire [`FLOORS-1:0] car1_assign;
    wire [`FLOORS-1:0] car2_assign;
    wire [2:0] car1_floor;
    wire [2:0] car2_floor;
    wire car1_moving, car2_moving;

    dual_elevator_controller dut(
        .clk(clk), .rst(rst), .hall_up(hall_up), .hall_down(hall_down), .car1_req(car1_req), .car2_req(car2_req),
        .car1_assign(car1_assign), .car2_assign(car2_assign), .car1_floor(car1_floor), .car2_floor(car2_floor), .car1_moving(car1_moving), .car2_moving(car2_moving)
    );

    always #5 clk = ~clk;

    initial begin
        $dumpfile("dual_elevator.vcd");
        $dumpvars(0, dut);

        hall_up = 0; hall_down = 0; car1_req = 0; car2_req = 0;

        #12 rst = 0;

        #10 hall_up[2] = 1;
        #50 hall_down[5] = 1;
        #50 car1_req[0] = 1; 
        #80 hall_up[1] = 1;

        #500 $finish;
    end

    always @(posedge clk) begin
        if (!rst) begin
            $display("time=%0t car1_floor=%0d car2_floor=%0d car1_m=%b car2_m=%b car1_assign=%b car2_assign=%b", $time, car1_floor, car2_floor, car1_moving, car2_moving, car1_assign, car2_assign);
        end
    end

endmodule

dual_elevator.vcd
$date
	Sat Oct 04 12:51:55 2025
$end
$version
	Icarus Verilog
$end
$timescale
	1ps
$end
$scope module dual_elevator_tb $end
$scope module dut $end
$var wire 6 ! car1_assign [5:0] $end
$var wire 6 " car1_req [5:0] $end
$var wire 6 # car2_assign [5:0] $end
$var wire 6 $ car2_req [5:0] $end
$var wire 1 % clk $end
$var wire 6 & combined [5:0] $end
$var wire 6 ' hall_down [5:0] $end
$var wire 6 ( hall_up [5:0] $end
$var wire 1 ) rst $end
$var wire 1 * car2_moving $end
$var wire 3 + car2_floor [2:0] $end
$var wire 1 , car1_moving $end
$var wire 3 - car1_floor [2:0] $end
$var parameter 32 . MID $end
$var reg 6 / assign1 [5:0] $end
$var reg 6 0 assign2 [5:0] $end
$var integer 32 1 j [31:0] $end
$scope module car1 $end
$var wire 1 % clk $end
$var wire 6 2 requests [5:0] $end
$var wire 1 ) rst $end
$var parameter 32 3 ID $end
$var reg 3 4 current_floor [2:0] $end
$var reg 1 , moving $end
$var reg 6 5 pending [5:0] $end
$var integer 32 6 i [31:0] $end
$var integer 32 7 target [31:0] $end
$upscope $end
$scope module car2 $end
$var wire 1 % clk $end
$var wire 6 8 requests [5:0] $end
$var wire 1 ) rst $end
$var parameter 32 9 ID $end
$var reg 3 : current_floor [2:0] $end
$var reg 1 * moving $end
$var reg 6 ; pending [5:0] $end
$var integer 32 < i [31:0] $end
$var integer 32 = target [31:0] $end
$upscope $end
$upscope $end
$upscope $end
$enddefinitions $end
$comment Show the parameter values. $end
$dumpall
b10 9
b1 3
b11 .
$end
#0
$dumpvars
bx =
bx <
b0 ;
b0 :
b0 8
bx 7
bx 6
b0 5
b0 4
b0 2
b110 1
b0 0
b0 /
b0 -
0,
b0 +
0*
1)
b0 (
b0 '
b0 &
0%
b0 $
b0 #
b0 "
b0 !
$end
#5000
1%
#10000
0%
#12000
0)
#15000
1%
#20000
0%
#22000
b100 !
b100 /
b100 2
b110 1
b100 &
b100 (
#25000
b100 5
1%
#30000
0%
#35000
b1 -
b1 4
1,
b111 6
b10 7
1%
#40000
0%
#45000
b10 -
b10 4
b111 6
b10 7
1%
#50000
0%
#55000
b0 5
b111 6
b10 7
1%
#60000
0%
#65000
0,
b100 5
1%
#70000
0%
#72000
b100000 #
b100000 0
b100000 8
b110 1
b100 !
b100 /
b100 2
b100100 &
b100000 '
#75000
b0 5
1,
b100000 ;
b111 6
b10 7
1%
#80000
0%
#85000
b1 +
b1 :
1*
0,
b100 5
b111 <
b101 =
1%
#90000
0%
#95000
b0 5
1,
b10 +
b10 :
b111 6
b10 7
b111 <
b101 =
1%
#100000
0%
#105000
b11 +
b11 :
0,
b100 5
b111 <
b101 =
1%
#110000
0%
#115000
b0 5
1,
b100 +
b100 :
b111 6
b10 7
b111 <
b101 =
1%
#120000
0%
#122000
b110 1
b100000 #
b100000 0
b100000 8
b101 !
b101 /
b101 2
b100101 &
b1 "
#125000
b101 +
b101 :
0,
b101 5
b111 <
b101 =
1%
#130000
0%
#135000
b1 -
b1 4
1,
b0 ;
b111 6
b0 7
b111 <
b101 =
1%
#140000
0%
#145000
0*
b100000 ;
b0 -
b0 4
b111 6
b0 7
1%
#150000
0%
#155000
b100 5
b0 ;
1*
b111 6
b0 7
b111 <
b101 =
1%
#160000
0%
#165000
0*
b100000 ;
b1 -
b1 4
b101 5
b111 6
b10 7
1%
#170000
0%
#175000
b0 -
b0 4
b0 ;
1*
b111 6
b0 7
b111 <
b101 =
1%
#180000
0%
#185000
0*
b100000 ;
b100 5
b111 6
b0 7
1%
#190000
0%
#195000
b1 -
b1 4
b101 5
b0 ;
1*
b111 6
b10 7
b111 <
b101 =
1%
#200000
0%
#202000
b110 1
b100000 #
b100000 0
b100000 8
b111 !
b111 /
b111 2
b100111 &
b110 (
#205000
0*
b100000 ;
b0 -
b0 4
b111 5
b111 6
b0 7
1%
#210000
0%
#215000
b110 5
b0 ;
1*
b111 6
b0 7
b111 <
b101 =
1%
#220000
0%
#225000
0*
b100000 ;
b1 -
b1 4
b111 5
b111 6
b1 7
1%
#230000
0%
#235000
b0 -
b0 4
b0 ;
1*
b111 6
b0 7
b111 <
b101 =
1%
#240000
0%
#245000
0*
b100000 ;
b110 5
b111 6
b0 7
1%
#250000
0%
#255000
b1 -
b1 4
b111 5
b0 ;
1*
b111 6
b1 7
b111 <
b101 =
1%
#260000
0%
#265000
0*
b100000 ;
b0 -
b0 4
b111 6
b0 7
1%
#270000
0%
#275000
b110 5
b0 ;
1*
b111 6
b0 7
b111 <
b101 =
1%
#280000
0%
#285000
0*
b100000 ;
b1 -
b1 4
b111 5
b111 6
b1 7
1%
#290000
0%
#295000
b0 -
b0 4
b0 ;
1*
b111 6
b0 7
b111 <
b101 =
1%
#300000
0%
#305000
0*
b100000 ;
b110 5
b111 6
b0 7
1%
#310000
0%
#315000
b1 -
b1 4
b111 5
b0 ;
1*
b111 6
b1 7
b111 <
b101 =
1%
#320000
0%
#325000
0*
b100000 ;
b0 -
b0 4
b111 6
b0 7
1%
#330000
0%
#335000
b110 5
b0 ;
1*
b111 6
b0 7
b111 <
b101 =
1%
#340000
0%
#345000
0*
b100000 ;
b1 -
b1 4
b111 5
b111 6
b1 7
1%
#350000
0%
#355000
b0 -
b0 4
b0 ;
1*
b111 6
b0 7
b111 <
b101 =
1%
#360000
0%
#365000
0*
b100000 ;
b110 5
b111 6
b0 7
1%
#370000
0%
#375000
b1 -
b1 4
b111 5
b0 ;
1*
b111 6
b1 7
b111 <
b101 =
1%
#380000
0%
#385000
0*
b100000 ;
b0 -
b0 4
b111 6
b0 7
1%
#390000
0%
#395000
b110 5
b0 ;
1*
b111 6
b0 7
b111 <
b101 =
1%
#400000
0%
#405000
0*
b100000 ;
b1 -
b1 4
b111 5
b111 6
b1 7
1%
#410000
0%
#415000
b0 -
b0 4
b0 ;
1*
b111 6
b0 7
b111 <
b101 =
1%
#420000
0%
#425000
0*
b100000 ;
b110 5
b111 6
b0 7
1%
#430000
0%
#435000
b1 -
b1 4
b111 5
b0 ;
1*
b111 6
b1 7
b111 <
b101 =
1%
#440000
0%
#445000
0*
b100000 ;
b0 -
b0 4
b111 6
b0 7
1%
#450000
0%
#455000
b110 5
b0 ;
1*
b111 6
b0 7
b111 <
b101 =
1%
#460000
0%
#465000
0*
b100000 ;
b1 -
b1 4
b111 5
b111 6
b1 7
1%
#470000
0%
#475000
b0 -
b0 4
b0 ;
1*
b111 6
b0 7
b111 <
b101 =
1%
#480000
0%
#485000
0*
b100000 ;
b110 5
b111 6
b0 7
1%
#490000
0%
#495000
b1 -
b1 4
b111 5
b0 ;
1*
b111 6
b1 7
b111 <
b101 =
1%
#500000
0%
#505000
0*
b100000 ;
b0 -
b0 4
b111 6
b0 7
1%
#510000
0%
#515000
b110 5
b0 ;
1*
b111 6
b0 7
b111 <
b101 =
1%
#520000
0%
#525000
0*
b100000 ;
b1 -
b1 4
b111 5
b111 6
b1 7
1%
#530000
0%
#535000
b0 -
b0 4
b0 ;
1*
b111 6
b0 7
b111 <
b101 =
1%
#540000
0%
#545000
0*
b100000 ;
b110 5
b111 6
b0 7
1%
#550000
0%
#555000
b1 -
b1 4
b111 5
b0 ;
1*
b111 6
b1 7
b111 <
b101 =
1%
#560000
0%
#565000
0*
b100000 ;
b0 -
b0 4
b111 6
b0 7
1%
#570000
0%
#575000
b110 5
b0 ;
1*
b111 6
b0 7
b111 <
b101 =
1%
#580000
0%
#585000
0*
b100000 ;
b1 -
b1 4
b111 5
b111 6
b1 7
1%
#590000
0%
#595000
b0 -
b0 4
b0 ;
1*
b111 6
b0 7
b111 <
b101 =
1%
#600000
0%
#605000
0*
b100000 ;
b110 5
b111 6
b0 7
1%
#610000
0%
#615000
b1 -
b1 4
b111 5
b0 ;
1*
b111 6
b1 7
b111 <
b101 =
1%
#620000
0%
#625000
0*
b100000 ;
b0 -
b0 4
b111 6
b0 7
1%
#630000
0%
#635000
b110 5
b0 ;
1*
b111 6
b0 7
b111 <
b101 =
1%
#640000
0%
#645000
0*
b100000 ;
b1 -
b1 4
b111 5
b111 6
b1 7
1%
#650000
0%
#655000
b0 -
b0 4
b0 ;
1*
b111 6
b0 7
b111 <
b101 =
1%
#660000
0%
#665000
0*
b100000 ;
b110 5
b111 6
b0 7
1%
#670000
0%
#675000
b1 -
b1 4
b111 5
b0 ;
1*
b111 6
b1 7
b111 <
b101 =
1%
#680000
0%
#685000
0*
b100000 ;
b0 -
b0 4
b111 6
b0 7
1%
#690000
0%
#695000
b110 5
b0 ;
1*
b111 6
b0 7
b111 <
b101 =
1%
